acd/__init__.py
acd/api.py
acd/database/__init__.py
acd/database/acd_database.py
acd/database/dbextract.py
acd/database/sql_database_provider.py
acd/exceptions/CompsRecordException.py
acd/exceptions/__init__.py
acd/generated/__init__.py
acd/generated/dat.py
acd/generated/comments/__init__.py
acd/generated/comments/fafa_coments.py
acd/generated/comps/__init__.py
acd/generated/comps/fafa_comps.py
acd/generated/comps/fdfd_comps.py
acd/generated/comps/rx_generic.py
acd/generated/comps/rx_tag.py
acd/generated/controller/__init__.py
acd/generated/controller/rx_controller.py
acd/generated/map_device/__init__.py
acd/generated/map_device/rx_map_device.py
acd/generated/sbregion/__init__.py
acd/generated/sbregion/fafa_sbregions.py
acd/l5x/__init__.py
acd/l5x/elements.py
acd/l5x/export_l5x.py
acd/record/__init__.py
acd/record/comments.py
acd/record/comps.py
acd/record/nameless.py
acd/record/sbregion.py
acd/zip/__init__.py
acd/zip/unzip.py
acd_tools-0.2a8.dist-info/LICENSE
acd_tools-0.2a8.dist-info/METADATA
acd_tools-0.2a8.dist-info/WHEEL
acd_tools-0.2a8.dist-info/top_level.txt
acd_tools-0.2a8.dist-info/RECORD
