Metadata-Version: 2.1
Name: acd-tools
Version: 0.2a8
Summary: Rockwell ACD File Tools
Home-page: https://github.com/hutcheb/acd
Author: Ben Hutcheson
Author-email: 
License: Apache 2.0
Keywords: rockwell acd logix
Classifier: Development Status :: 3 - Alpha
Classifier: License :: OSI Approved :: Apache Software License
Classifier: Programming Language :: Python :: 3.8
Classifier: Topic :: Scientific/Engineering :: Interface Engine/Protocol Translator
License-File: LICENSE
Requires-Dist: loguru
Requires-Dist: kaitaistruct
Provides-Extra: dev
Requires-Dist: requires ; extra == 'dev'
Requires-Dist: pytest-asyncio ; extra == 'dev'
Requires-Dist: pip-tools ; extra == 'dev'
Requires-Dist: pre-commit ; extra == 'dev'
Requires-Dist: pytest-mock ; extra == 'dev'
Requires-Dist: mock ; extra == 'dev'
Requires-Dist: mypy ; extra == 'dev'
